json_jsonl/__init__.py
json_jsonl/__json_jsonl.py
json_jsonl-0.0.6.dist-info/METADATA
json_jsonl-0.0.6.dist-info/RECORD
json_jsonl-0.0.6.dist-info/WHEEL
json_jsonl-0.0.6.dist-info/metadata.json
json_jsonl-0.0.6.dist-info/top_level.txt
