Metadata-Version: 2.0
Name: json-jsonl
Version: 0.0.6
Summary: json, jsonl
Home-page: https://github.com/INGPlay/json_jsonl
Author: 김병주
Author-email: atker14@gmail.com
Classifier: Programming Language :: Python :: 3
Classifier: License :: OSI Approved :: MIT License
Classifier: Operating System :: OS Independent
Requires-Python: >=3
